cxc_mq/__init__.py
cxc_mq/consume.py
cxc_mq/mixins.py
cxc_mq/publish.py
cxc_mq-0.0.7.dist-info/DESCRIPTION.rst
cxc_mq-0.0.7.dist-info/METADATA
cxc_mq-0.0.7.dist-info/RECORD
cxc_mq-0.0.7.dist-info/WHEEL
cxc_mq-0.0.7.dist-info/metadata.json
cxc_mq-0.0.7.dist-info/top_level.txt
