Metadata-Version: 2.0
Name: cxc-mq
Version: 0.0.7
Summary: Message queue library
Home-page: https://github.com/XiaochenCui/cxc-mq
Author: Xiaochen Cui
Author-email: jcnlcxc.new@gmail.com
License: GPLv3
Platform: UNKNOWN
Classifier: Development Status :: 1 - Planning
Classifier: Intended Audience :: Developers
Classifier: Topic :: Software Development :: Libraries :: Python Modules
Classifier: License :: OSI Approved :: GNU General Public License v3 (GPLv3)
Classifier: Programming Language :: Python :: 3
Classifier: Programming Language :: Python :: 3.6
Classifier: Programming Language :: Python :: 3 :: Only
Requires-Dist: pika
Requires-Dist: cxc-toolkit
